setup.py
aliyun_cs_tools/__init__.py
aliyun_cs_tools.egg-info/PKG-INFO
aliyun_cs_tools.egg-info/SOURCES.txt
aliyun_cs_tools.egg-info/dependency_links.txt
aliyun_cs_tools.egg-info/requires.txt
aliyun_cs_tools.egg-info/top_level.txt
aliyun_cs_tools/core/__init__.py
aliyun_cs_tools/core/manager.py