Metadata-Version: 1.1
Name: aliyun-cs-tools
Version: 0.1
Summary: library for aliyun container service management
Home-page: UNKNOWN
Author: wangying
Author-email: wangying@dragonest.com
License: LGPL
Platform: UNKNOWN
Classifier: Programming Language :: Python :: 2.7
Classifier: Topic :: Software Development :: Libraries :: Python Modules
